target_snowflake/__init__.py
target_snowflake/db_sync.py
target_snowflake/exceptions.py
target_snowflake/file_format.py
target_snowflake/flattening.py
target_snowflake/stream_utils.py
target_snowflake/file_formats/__init__.py
target_snowflake/file_formats/csv.py
target_snowflake/file_formats/parquet.py
target_snowflake/upload_clients/__init__.py
target_snowflake/upload_clients/base_upload_client.py
target_snowflake/upload_clients/s3_upload_client.py
target_snowflake/upload_clients/snowflake_upload_client.py
oc_pipelinewise_target_snowflake-2.2.0.dist-info/LICENSE
oc_pipelinewise_target_snowflake-2.2.0.dist-info/METADATA
oc_pipelinewise_target_snowflake-2.2.0.dist-info/WHEEL
oc_pipelinewise_target_snowflake-2.2.0.dist-info/entry_points.txt
oc_pipelinewise_target_snowflake-2.2.0.dist-info/top_level.txt
oc_pipelinewise_target_snowflake-2.2.0.dist-info/RECORD
