Metadata-Version: 2.1
Name: oc-pipelinewise-target-snowflake
Version: 2.2.0
Summary: Singer.io target for loading data to Snowflake - PipelineWise compatible
Home-page: https://github.com/transferwise/pipelinewise-target-snowflake
Author: Wise
Classifier: License :: OSI Approved :: Apache Software License
Classifier: Programming Language :: Python :: 3 :: Only
Classifier: Programming Language :: Python :: 3.7
Classifier: Programming Language :: Python :: 3.8
Classifier: Programming Language :: Python :: 3.9
Requires-Python: >=3.7
License-File: LICENSE
Requires-Dist: pipelinewise-singer-python (==1.*)
Requires-Dist: snowflake-connector-python[pandas] (==3.0.*)
Requires-Dist: inflection (==0.5.1)
Requires-Dist: joblib (==1.2.0)
Requires-Dist: boto3 (==1.26.147)
Provides-Extra: test
Requires-Dist: pylint (==2.12.*) ; extra == 'test'
Requires-Dist: pytest (==7.1.1) ; extra == 'test'
Requires-Dist: pytest-cov (==3.0.0) ; extra == 'test'
Requires-Dist: python-dotenv (==0.19.*) ; extra == 'test'
